nombres_arg/__init__.py
nombres_arg/config.py
nombres_arg/data_loader.py
nombres_arg/data_processing.py
nombres_arg/logging_config.py
nombres_arg/utils.py
nombres_arg-0.4.10.dist-info/licenses/LICENSE
nombres_arg-0.4.10.dist-info/METADATA
nombres_arg-0.4.10.dist-info/WHEEL
nombres_arg-0.4.10.dist-info/top_level.txt
nombres_arg-0.4.10.dist-info/RECORD
