Metadata-Version: 2.4
Name: nombres-arg
Version: 0.4.10
Summary: A package for accessing names and last names from Argentina.
Home-page: https://github.com/adrian-alejandro/nombres-arg
Author: Adrián Zelaya
Author-email: Adrián Zelaya <zelaya.adrian@gmail.com>
License: Creative Commons Legal Code
Requires-Python: >=3.8
License-File: LICENSE
Requires-Dist: pandas
Requires-Dist: requests
Requires-Dist: spacy
Provides-Extra: dev
Requires-Dist: pytest; extra == "dev"
Dynamic: author
Dynamic: license-file
Dynamic: requires-python
